bolinette/data/README.md
bolinette/data/__init__.py
bolinette/data/databases.py
bolinette/data/defaults/__init__.py
bolinette/data/defaults/arg_resolvers.py
bolinette/data/defaults/commands.py
bolinette/data/defaults/databases.py
bolinette/data/defaults/mapper.py
bolinette/data/exceptions.py
bolinette/data/extension.py
bolinette/data/objects.py
bolinette/data/py.typed
bolinette/data/pyproject.toml
bolinette/data/relational/__init__.py
bolinette/data/relational/base.py
bolinette/data/relational/database.py
bolinette/data/relational/entity.py
bolinette/data/relational/manager.py
bolinette/data/relational/repository.py
bolinette/data/relational/service.py
bolinette/data/relational/session.py
bolinette/data/relational/transaction.py
bolinette_data-0.18.2.dist-info/LICENSE.txt
bolinette_data-0.18.2.dist-info/METADATA
bolinette_data-0.18.2.dist-info/WHEEL
bolinette_data-0.18.2.dist-info/RECORD
