Metadata-Version: 2.1
Name: bolinette-data
Version: 0.18.2
Summary: The Bolinette data package, an async data management framework, based on Bolinette and SQLAlchemy
Home-page: https://bolinette.org
License: MIT
Keywords: Bolinette,Framework,ORM,Data Management
Author: Pierre Chat
Author-email: pierrechat@outlook.com
Requires-Python: >=3.12,<4.0
Classifier: Development Status :: 4 - Beta
Classifier: Intended Audience :: Developers
Classifier: License :: OSI Approved :: MIT License
Classifier: Programming Language :: Python :: 3
Classifier: Programming Language :: Python :: 3.12
Classifier: Topic :: Software Development :: Build Tools
Requires-Dist: aiosqlite (>=0.19.0,<0.20.0)
Requires-Dist: asyncpg (>=0.28.0,<0.29.0)
Requires-Dist: bolinette (>=0.18.2,<0.19.0)
Requires-Dist: sqlalchemy (>=2.0.18,<3.0.0)
Project-URL: Documentation, https://bolinette.org/docs
Project-URL: Repository, https://github.com/bolinette/bolinette
